{
    "Utiliza ou j\u00e1 utilizou transportes p\u00fablicos?": {
        "N\u00e3o": 1,
        "Total": 274,
        "N\u00e3o Responderam": 0,
        "Sim": 273
    },
    "Idade": {
        "25 \u2014 30": 27,
        "Mais de 60": 1,
        "Menos de 18 anos": 12,
        "N\u00e3o Responderam": 0,
        "Total": 274,
        "46 \u2014 60": 10,
        "31 \u2014 45": 11,
        "18 \u2014 24": 213
    },
    "O que acha de transportes p\u00fablicos sem barreiras f\u00edsicas?": {
        "\u00c9-me indiferente": 109,
        "Total": 274,
        "N\u00e3o Responderam": 1,
        "\u00c9 arquitetonicamente feio e  pouco funcional": 13,
        "\u00c9 arquitetonicamente bonito, mas pouco funcional": 99,
        "\u00c9 arquitetonicamente bonito e funcional": 52
    },
    "Com que frequ\u00eancia utiliza transportes p\u00fablicos?": {
        "Total": 274,
        "Raramente": 29,
        "N\u00e3o Responderam": 0,
        "Algumas vezes por m\u00eas": 36,
        "Diariamente": 169,
        "Algumas vezes por semana": 40
    },
    "Que t\u00edtulo de transporte costuma adquirir?": {
        "Total": 274,
        "N\u00e3o Responderam": 1,
        "Passes mensais em Lx, bilhetes fora.": 1,
        "Bilhete \u00fanico": 42,
        "Passe mensal": 178,
        "Carregamento recarreg\u00e1vel com saldo (ex: Zapping)": 52
    },
    "Com que frequ\u00eancia ADQUIRE o seu t\u00edtulo de transporte?": {
        "Total": 274,
        "Raramente": 5,
        "N\u00e3o Responderam": 124,
        "Nunca": 2,
        "Quase sempre": 123,
        "Algumas vezes": 10,
        "Muitas vezes": 10
    },
    "Em que cidade(s) j\u00e1 utilizou transportes p\u00fablicos?": {
        "Lisboa, Porto, Amsterd\u00e3o": 1,
        "Lisboa, Porto, Madrid, Barcelona, Paris": 2,
        "N\u00e3o Responderam": 0,
        "Lisboa, Porto, Madrid, Paris, Londres, Coimbra": 1,
        "Lisboa, Londres": 10,
        "Lisboa, Barcelona, Londres": 3,
        "Lisboa, Porto, Paris, Londres, Mil\u00e3o, Roma": 1,
        "Lisboa, Londres, Tokyo": 1,
        "Total": 274,
        "LAGOS": 1,
        "Lisboa, Viseu": 1,
        "Lisboa, Barcelona, Paris, Londres": 6,
        "Lisboa, Madrid, Barcelona": 2,
        "Lisboa, Paris, Delft, Amesterd\u00e3o, Roterd\u00e3o e Aia": 1,
        "Lisboa, Paris, Graz, Viena, Budapeste": 1,
        "Viana do Castelo": 1,
        "Lisboa, Porto, Madrid, Londres, Nova Iorque, Amesterd\u00e3o": 1,
        "Lisboa, Londres, Delft, Amesterd\u00e3o, Haia": 1,
        "Lisboa, Madrid, Paris, Londres": 2,
        "Lisboa, Porto, Madrid, Londres": 3,
        "Lisboa, Madrid, Barcelona, Paris": 2,
        "Lisboa, Porto, Paris, Londres, Singapura": 1,
        "Lisboa, Barcelona, Paris, Londres, Nova Iorque": 1,
        "Leiria ": 1,
        "Lisboa, Porto, Madrid, Londres, Roma": 1,
        "Lisboa, Montijo, Setubal": 1,
        "Lisboa, Madrid, Barcelona, Paris, Londres": 7,
        "Lisboa, Porto, Madrid, Paris, Londres, Viena, Amsterd\u00e3o": 1,
        "Lisboa, Porto, Madrid, Paris, Londres": 6,
        "Lisboa, Porto, Paris, Londres, Berlim; Budapeste": 1,
        "Lisboa, Porto, Genebra": 1,
        "Lisboa, Porto, Barcelona, Londres": 5,
        "Beja": 1,
        "Lisboa, Madrid, Barcelona, Paris, Londres, Copenhaga, Genebra": 1,
        "Lisboa, Porto, Madrid, Paris": 1,
        "Lisboa, Su\u00ed\u00e7a ": 1,
        "Lisboa, Paris, Praga": 1,
        "Lisboa, Porto, N\u00e1poles, Floren\u00e7a, Praga, Viena, Budapeste": 1,
        "Lisboa, Paris, Londres": 12,
        "Lisboa, Madrid, Londres, Roma": 1,
        "Lisboa, Madrid, Barcelona, Paris, Londres, Su\u00e9cia": 1,
        "Lisboa, Porto, Paris, Londres, Berlim": 1,
        "Lisboa, Porto, Madrid, Barcelona, Paris, Londres, Praga, berlim, basileia": 1,
        "Lisboa, Porto, Madrid, Paris, Londres, Roma, Praga, Budapeste, Viena": 1,
        "Lisboa, Porto, Paris, Londres, Budapeste": 1,
        "Lisboa, Madrid, Barcelona, Londres": 2,
        "Lisboa, Paris, Londres, Funchal, Marselha, Estocolmo, Copenhaga": 1,
        "Lisboa, Porto, Barcelona, Paris, Londres": 5,
        "Lisboa, Porto, Set\u00fabal ": 1,
        "Lisboa, Caldas da Rainha": 1,
        "Lisboa, Porto, Covilh\u00e3": 1,
        "Lisboa, Roma": 1,
        "Lisboa, Porto, Vendas Novas": 1,
        "Lisboa, Porto, Madrid, Barcelona, Londres, Covilh\u00e3": 1,
        "Lisboa, Madrid, Barcelona, Paris, Londres, Hamburgo ": 1,
        "Lisboa, Porto": 24,
        "Lisboa, Madrid": 4,
        "Lisboa, Porto, Madrid, Barcelona, Paris, Londres, Por exemplo, em muitas outras capitais Europeias e Asi\u00e1ticas": 1,
        "Lisboa, Beja": 1,
        "Lisboa, Porto, Madrid, Londres, Praga, Vars\u00f3via, Crac\u00f3via, Budapeste, Bratislava, Viena": 1,
        "Lisboa, Genebra": 1,
        "Paris": 1,
        "Lisboa, Porto, Londres": 8,
        "Lisboa, Porto, Hels\u00ednquia ": 2,
        "Lisboa, Madrid, Paris, Londres, Toquio, seul, pequim, kuala lumpur, colonia, glasgow, dublim, liege,oslo, geneve, norfolk, quito, e outras mais": 1,
        "Lisboa, Porto, Madrid, Barcelona": 2,
        "Lisboa, Porto, Madrid, Barcelona, Paris, Londres": 9,
        "Lisboa, Porto, Paris, Roma": 2,
        "Lisboa, Porto, Madrid, Barcelona, Paris, Londres, Amsterd\u00e3o, Roma, Mil\u00e3o": 1,
        "Lisboa, Madrid, Paris, Londres, Mil\u00e3o": 1,
        "Lisboa, Porto, Madrid, Barcelona, Londres, Pa\u00edses Baixos, It\u00e1lia...": 1,
        "Porto, Guimar\u00e3es": 1,
        "Lisboa, Barcelona": 2,
        "\u00c9vora ": 1,
        "Porto, Madrid": 1,
        "Lisboa, Porto, Barcelona, Paris, Londres, Faro e Oslo": 1,
        "Lisboa, Madrid, Londres": 3,
        "Lisboa, Porto, Paris, Londres, Washington DC, Boston, New York, Crac\u00f3via, Los Angeles, New Orleans, Genebra, New Jersey, Chicago, San Francisco": 1,
        "Lisboa, Porto, \u00c9vora": 1,
        "Lisboa, Porto, Paris": 6,
        "Lisboa, Londres, Funchal": 1,
        "Lisboa, Porto, Madrid, Almada, Praga": 1,
        "Lisboa": 53,
        "Lisboa, Paris": 10,
        "Lisboa, Mil\u00e3o, Atenas": 1,
        "Lisboa, Barcelona, Londres, Nova Iorque, Roma": 1,
        "Lisboa, Faro": 1,
        "Lisboa, Madrid, Londres, Praga": 1,
        "Lisboa, Porto, Paris, Londres": 5,
        "Lisboa, Madrid, Paris, Praga, roma, veneza, floren\u00e7a, bruxelas, gent ": 1,
        "Lisboa, Barcelona, Paris": 2,
        "Lisboa, Porto, Madrid, Barcelona, Paris, Viena, Budapeste, Berlim, Amesterd\u00e3o ": 1,
        "Lisboa, Porto, Coimbra": 1,
        "Lisboa, Porto, Madrid, Barcelona, Londres": 2,
        "Lisboa, Setubal": 1,
        "Porto": 5,
        "Lisboa, \u00c9vora": 1,
        "Lisboa, Porto, Madrid, Budapeste": 1,
        "Lisboa, Porto, Barcelona": 2
    },
    "Qu\u00e3o justo considera o pre\u00e7o do t\u00edtulo de transporte, tendo em conta o servi\u00e7o prestado?": {
        "5.0": 47,
        "8.0": 31,
        "N\u00e3o Responderam": 1,
        "10.0": 8,
        "2.0": 12,
        "9.0": 11,
        "Total": 274,
        "3.0": 24,
        "1.0": 8,
        "6.0": 49,
        "7.0": 44,
        "4.0": 39
    },
    "G\u00e9nero": {
        "Outro": 3,
        "Feminino": 127,
        "Total": 274,
        "Masculino": 144,
        "N\u00e3o Responderam": 0
    },
    "Qu\u00e3o \u00fatil considera poder consultar hor\u00e1rios, pre\u00e7os e outras informa\u00e7\u00f5es sobre o transporte p\u00fablico numa aplica\u00e7\u00e3o m\u00f3vel?": {
        "8": 24,
        "7": 8,
        "N\u00e3o Responderam": 0,
        "6": 6,
        "10": 188,
        "Total": 274,
        "9": 39,
        "5": 3,
        "3": 2,
        "4": 2,
        "2": 1,
        "1": 1
    },
    "Principal motivo de usar transporte p\u00fablico": {
        "Escola": 11,
        "Total": 274,
        "Passear": 51,
        "Universidade": 182,
        "Atividades em Geral": 76,
        "Trabalho": 30
    },
    "Como classifica o seu n\u00edvel de satisfa\u00e7\u00e3o com os transportes p\u00fablicos que utiliza?": {
        "8": 41,
        "7": 61,
        "N\u00e3o Responderam": 0,
        "6": 64,
        "10": 2,
        "Total": 274,
        "9": 5,
        "5": 38,
        "3": 22,
        "4": 29,
        "2": 7,
        "1": 5
    },
    "Com que frequ\u00eancia VALIDA o seu t\u00edtulo de transporte?": {
        "Total": 274,
        "Raramente": 5,
        "N\u00e3o Responderam": 124,
        "Nunca": 2,
        "Quase sempre": 124,
        "Algumas vezes": 9,
        "Muitas vezes": 10
    },
    "Ocupa\u00e7\u00e3o": {
        "Empregado": 34,
        "Total": 274,
        "Estudante": 215,
        "N\u00e3o Responderam": 0,
        "Desempregado": 1,
        "Reformado": 1,
        "Trabalhador-Estudante": 23
    },
    "Considera que a aquisi\u00e7\u00e3o e valida\u00e7\u00e3o de t\u00edtulos de transporte atrav\u00e9s da aplica\u00e7\u00e3o m\u00f3vel iria aumentar se isso permitisse ganhar pr\u00e9mios (tais como viagens e descontos) aos utilizadores?": {
        "N\u00e3o": 26,
        "Total": 274,
        "N\u00e3o Responderam": 0,
        "Sim": 248
    },
    "Que tipo de transportes p\u00fablicos utiliza?": {
        "Metro": 28,
        "Metro, Autocarro, Comboio, Barco, El\u00e9trico": 1,
        "N\u00e3o Responderam": 0,
        "Metro, Autocarro, Comboio, Barco": 5,
        "El\u00e9trico": 1,
        "Metro, Autocarro, Barco": 2,
        "Autocarro": 14,
        "Metro, Bicicletas GIRA": 1,
        "Autocarro, Comboio": 17,
        "Metro, Autocarro, Bicicleta": 1,
        "Total": 274,
        "Metro, Barco": 5,
        "Metro, Autocarro": 87,
        "Comboio": 16,
        "Metro, Comboio, Barco": 1,
        "Metro, Autocarro, Comboio, El\u00e9trico": 2,
        "Metro, Comboio": 42,
        "Metro, Autocarro, Comboio": 51
    },
    "Qu\u00e3o \u00fatil considera poder adquirir e/ou usar os seus t\u00edtulos de transporte atrav\u00e9s de uma aplica\u00e7\u00e3o m\u00f3vel?": {
        "8": 40,
        "7": 31,
        "N\u00e3o Responderam": 0,
        "6": 12,
        "10": 133,
        "Total": 274,
        "9": 28,
        "5": 11,
        "3": 5,
        "4": 4,
        "2": 5,
        "1": 5
    },
    "J\u00e1 utilizou algum transporte p\u00fablico sem validar ou adquirir o t\u00edtulo de transporte?": {
        "N\u00e3o": 123,
        "Total": 274,
        "N\u00e3o Responderam": 1,
        "Sim": 150
    },
    "Indique todas as raz\u00f5es pelas quais n\u00e3o validou e/ou adquiriu o t\u00edtulo de transporte:": {
        "N\u00e3o encontrei ponto de valida\u00e7\u00e3o (comboio) ": 1,
        "Pressa para apanhar o transporte p\u00fablico, os autocarros noturnos n\u00e3o vale a pena": 1,
        "Pressa para apanhar o transporte p\u00fablico, M\u00e1quina de bilheteira n\u00e3o funcionava, Tenho passe mensal, o pre\u00e7o n\u00e3o se altera se validar mais ou menos vezes": 1,
        "Fila para adquirir o bilhete, Pressa para apanhar o transporte p\u00fablico, M\u00e1quina de bilheteira n\u00e3o funcionava": 12,
        "N\u00e3o Responderam": 124,
        "Aconteceu apenas uma vez, necessitava de ir a casa de um amigo fazer um trabalho e nenhum de n\u00f3s tinha dinheiro para o bilhete": 1,
        "Dificuldade a entender a interface da bilheteira, Pressa para apanhar o transporte p\u00fablico, M\u00e1quina de bilheteira n\u00e3o funcionava": 1,
        "Forgot": 1,
        "Don't know how the zones of the AndanteCard work.": 1,
        "Pre\u00e7o elevado, Pressa para apanhar o transporte p\u00fablico": 16,
        "Dificuldade a entender a interface da bilheteira, Pressa para apanhar o transporte p\u00fablico": 1,
        "Total": 274,
        "Pressa para apanhar o transporte p\u00fablico, M\u00e1quina de bilheteira n\u00e3o funcionava, Leitores que n\u00e3o funcionam": 1,
        "N me apeteceu": 1,
        "Pressa para apanhar o transporte p\u00fablico, Rebeldia": 1,
        "Pre\u00e7o elevado, Fila para adquirir o bilhete, Pressa para apanhar o transporte p\u00fablico": 5,
        "Pre\u00e7o elevado, Fila para adquirir o bilhete": 1,
        "Pressa para apanhar o transporte p\u00fablico": 28,
        "Pre\u00e7o elevado, M\u00e1quina de bilheteira n\u00e3o funcionava": 3,
        "M\u00e1quina de bilheteira n\u00e3o funcionava": 5,
        "Forretice": 1,
        "Pre\u00e7o elevado, Fila para adquirir o bilhete, Pressa para apanhar o transporte p\u00fablico, M\u00e1quina de bilheteira n\u00e3o funcionava": 1,
        "M\u00e1quina n\u00e3o tinha troco": 1,
        "Pressa para apanhar o transporte p\u00fablico, Falta de dinheiro": 1,
        "Fila para adquirir o bilhete, M\u00e1quina de bilheteira n\u00e3o funcionava, nao o tinha comigo": 1,
        "pq a merda do metro de lisboa deixa o meu bilhete inv\u00e1lido for no fucking reason": 1,
        "Pre\u00e7o elevado, Pressa para apanhar o transporte p\u00fablico, M\u00e1quina de bilheteira n\u00e3o funcionava": 6,
        "Eu uso passe boy, m\u00e1 interface. E o passe so precisa de uma valida\u00e7ao por m\u00eas": 1,
        "Fila para adquirir o bilhete": 1,
        "Pre\u00e7o elevado": 16,
        "Dificuldade a entender a interface da bilheteira, M\u00e1quina de bilheteira n\u00e3o funcionava": 2,
        "Pressa para apanhar o transporte p\u00fablico, M\u00e1quina de bilheteira n\u00e3o funcionava": 15,
        "Pressa para apanhar o transporte p\u00fablico, Esquecimento principalmente nos comboios": 1,
        "Transporte cheio e impossibilidade de chegar a maquina de validacao": 1,
        "Dificuldade a entender a interface da bilheteira, Fila para adquirir o bilhete, Pressa para apanhar o transporte p\u00fablico, M\u00e1quina de bilheteira n\u00e3o funcionava": 1,
        "Pressa para apanhar o transporte p\u00fablico, Esquecimento ": 2,
        "Fila para adquirir o bilhete, M\u00e1quina de bilheteira n\u00e3o funcionava": 1,
        "Pressa para apanhar o transporte p\u00fablico, M\u00e1quina de bilheteira n\u00e3o funcionava, Esquecimento": 1,
        "Paci\u00eancia, ou falta dela": 1,
        "Pressa para apanhar o transporte p\u00fablico, M\u00e1quina de bilheteira n\u00e3o funcionava, N\u00e3o encontrei a bilheteira ": 1,
        "Prefiro n\u00e3o divulgar.": 1,
        "Pre\u00e7o elevado, Dificuldade a entender a interface da bilheteira, Pressa para apanhar o transporte p\u00fablico": 1,
        "Fila para adquirir o bilhete, Pressa para apanhar o transporte p\u00fablico": 6,
        "Chegar atrasado porque sou gordo": 1,
        "Indisponibilidade de local para validar": 1,
        "Impossibilidade de chegar ao validador, dentro do transporte ": 1,
        "era mais uma paragem na zona a seguir": 1,
        "Pressa para apanhar o transporte p\u00fablico, Estava sem dinheiro.": 1
    }
}
